Metadata-Version: 1.0
Name: probability-dist-g-b
Version: 1.0
Summary: Gaussian and Binomial Distributions
Home-page: UNKNOWN
Author: Tasnuva Zaman
Author-email: tasnuvaleeya@gmail.com
License: UNKNOWN
Platform: UNKNOWN
